deqarclient/__init__.py
deqarclient/agency.py
deqarclient/api.py
deqarclient/auth.py
deqarclient/csv.py
deqarclient/errors.py
deqarclient/institution.py
deqarclient-1.0.0.data/scripts/importInstitutions.py
deqarclient-1.0.0.dist-info/METADATA
deqarclient-1.0.0.dist-info/WHEEL
deqarclient-1.0.0.dist-info/top_level.txt
deqarclient-1.0.0.dist-info/RECORD
