Metadata-Version: 2.1
Name: deqarclient
Version: 1.0.0
Summary: Python classes to work with DEQAR APIs
Home-page: https://github.com/EQAR/deqar-tools/
Download-URL: https://pypi.org/project/deqarclient/
Author: Colin Tück
Author-email: colin.tueck@eqar.eu
License: GPL
Keywords: DEQAR
Requires-Dist: coloredlogs
Requires-Dist: requests
Requires-Dist: tldextract
Requires-Dist: transliterate
